tf_efficientdet_lite2/LICENSE
tf_efficientdet_lite2/README.MD
tf_efficientdet_lite2/__init__.py
tf_efficientdet_lite2/requirements.txt
tf_efficientdet_lite2/thirdparty.json
tf_efficientdet_lite2-0.10.dist-info/LICENSE.rst
tf_efficientdet_lite2-0.10.dist-info/METADATA
tf_efficientdet_lite2-0.10.dist-info/WHEEL
tf_efficientdet_lite2-0.10.dist-info/top_level.txt
tf_efficientdet_lite2-0.10.dist-info/RECORD
