Metadata-Version: 2.1
Name: tf-efficientdet-lite2
Version: 0.10
Summary: Object detection with tensorflow
Home-page: https://github.com/hansalemaos/tf_efficientdet_lite2
Author: Johannes Fischer
Author-email: <aulasparticularesdealemaosp@gmail.com>
License: MIT
Keywords: tensorflow,object detection
Classifier: Development Status :: 4 - Beta
Classifier: Programming Language :: Python :: 3 :: Only
Classifier: Programming Language :: Python :: 3.9
Classifier: Topic :: Scientific/Engineering :: Visualization
Classifier: Topic :: Software Development :: Libraries :: Python Modules
Classifier: Topic :: Text Editors :: Text Processing
Classifier: Topic :: Text Processing :: General
Classifier: Topic :: Text Processing :: Indexing
Classifier: Topic :: Text Processing :: Filters
Classifier: Topic :: Utilities
License-File: LICENSE.rst
Requires-Dist: a-cv-imwrite-imread-plus
Requires-Dist: appdirs
Requires-Dist: opencv-python
Requires-Dist: pandas
Requires-Dist: regex
Requires-Dist: requests
Requires-Dist: subprocess-pipe
Requires-Dist: tensorflow
Requires-Dist: tensorflow-hub
